cvanmf/__init__.py
cvanmf/combine.py
cvanmf/data/ALL_AML/ALL_AML_counts.tsv.gz
cvanmf/data/ALL_AML/ALL_AML_feature_md.tsv.gz
cvanmf/data/ES5_W.tsv
cvanmf/data/NSCLC/nsclc.lung.composition.tsv.gz
cvanmf/data/NSCLC/nsclc.lung.metadata.tsv.gz
cvanmf/data/NW_ABUNDANCE.tsv
cvanmf/data/README.txt
cvanmf/data/__init__.py
cvanmf/data/swimmer/swimmer.tsv.gz
cvanmf/data/utils.py
cvanmf/denovo.py
cvanmf/models.py
cvanmf/reapply.py
cvanmf/stability.py
cvanmf-1.0.0.dist-info/METADATA
cvanmf-1.0.0.dist-info/WHEEL
cvanmf-1.0.0.dist-info/entry_points.txt
cvanmf-1.0.0.dist-info/licenses/LICENSE
cvanmf-1.0.0.dist-info/RECORD
