Metadata-Version: 2.4
Name: cvanmf
Version: 1.0.0
Summary: Bi-cross validation of NMF and signature generation and analysis
License: GNU General Public License v2.0
License-File: LICENSE
Author: Anthony Duncan
Requires-Python: >=3.12,<4.0
Classifier: License :: Other/Proprietary License
Classifier: Programming Language :: Python :: 3
Classifier: Programming Language :: Python :: 3.12
Classifier: Programming Language :: Python :: 3.13
Classifier: Programming Language :: Python :: 3.14
Requires-Dist: click (>=8.1.7,<9.0.0)
Requires-Dist: kneed (>=0.8.5,<0.9.0)
Requires-Dist: marsilea (>=0.4.3,<0.5.0)
Requires-Dist: multimethod (>=1.12,<2.0)
Requires-Dist: pandas (>=2.1.4,<3.0.0)
Requires-Dist: plotnine (>=0.13,<0.14)
Requires-Dist: pyyaml (>=6.0.1,<7.0.0)
Requires-Dist: scikit-bio (>=0.6.0,<0.7.0)
Requires-Dist: scikit-learn (>=1.3.2,<2.0.0)
Requires-Dist: scikit-posthocs (>=0.9.0,<0.10.0)
Requires-Dist: setuptools (>=69.1.1,<70.0.0)
Requires-Dist: tqdm (>=4.66.1,<5.0.0)
